tests/__init__.py
tests/test_config.py
tests/test_store.py
tests/test_fingers/__init__.py
tests/test_fingers/test_theme/__init__.py
tests/test_fingers/test_theme/test_crawler.py
tests/test_fingers/test_theme/test_finger.py
tests/test_fingers/test_theme/test_models.py
tests/test_validators/__init__.py
tests/test_validators/test_url.py
wpoke/__init__.py
wpoke/client.py
wpoke/conf.py
wpoke/exceptions.py
wpoke/finger.py
wpoke/hand.py
wpoke/store.py
wpoke/version.py
wpoke/bin/wpoke-cli
wpoke/bin/wpoke-cli.py
wpoke/fingers/__init__.py
wpoke/fingers/theme/__init__.py
wpoke/fingers/theme/crawler.py
wpoke/fingers/theme/models.py
wpoke/fingers/theme/serializers.py
wpoke/models/__init__.py
wpoke/validators/__init__.py
wpoke/validators/url.py
wpoke-0.1.4.data/scripts/wpoke-cli
wpoke-0.1.4.dist-info/LICENSE
wpoke-0.1.4.dist-info/METADATA
wpoke-0.1.4.dist-info/WHEEL
wpoke-0.1.4.dist-info/top_level.txt
wpoke-0.1.4.dist-info/RECORD
